lyn_env/__init__.py
lyn_env/envs/__init__.py
lyn_env/envs/env_lyn.py
lyn_env-0.0.9.dist-info/METADATA
lyn_env-0.0.9.dist-info/WHEEL
lyn_env-0.0.9.dist-info/top_level.txt
lyn_env-0.0.9.dist-info/RECORD
