Metadata-Version: 2.1
Name: lyn-env
Version: 0.0.9
Summary: A OpenAI Env for lyn
Requires-Dist: gym
